{"type": "root", "attrs": {"type": "include"}, "body": [{"tag": "div", "attrs": {"style": "position: relative;"}, "type": "xml", "text": ["\n    ", {"tag": "div", "attrs": {"style": "float: left; width: 5em;"}, "type": "xml", "text": ["\n        ", {"scheme": "Image", "value": "/images/beta.svg", "type": "link", "text": "", "fullpath": "/images/beta.svg"}, "\n    "]}, "\n    ", {"tag": "div", "attrs": {"style": "margin-left: 5em; padding-left: 1em; min-height: 4em;"}, "type": "xml", "text": ["\n        This feature is still under development. The current functionality is\n        unfinished and subject to change, and may have thin or no documentation.\n        Please bear this in mind when using it.\n    "]}, "\n"]}]}