{"type": "root", "attrs": {"type": "include"}, "body": [{"type": "para", "indent": 0, "text": ["Most dynamics nodes have local variables with the same names as the\nnode\u2019s parameters. For example, in a ", {"scheme": "Node", "value": "/nodes/dop/position", "type": "link", "text": ["Position node"], "fullpath": "/nodes/dop/position"}, ",\nyou could write the expression:"], "extent": [16, 189]}, {"lang": null, "type": "pre", "indent": 0, "text": ["\n$tx + 0.1\n"], "extent": [189, 207]}, {"type": "para", "indent": 0, "text": ["\u2026to make the object move 0.1 units along the X axis at each timestep."], "extent": [207, 280]}]}